Workbook

Sheet Read me
A1: HolyPearls end-to-end manual QA matrix
A2: Generated | B2: 2026-10-28, from dev at 1ad966e
A3: Staging web | B3: https://holypearls-git-dev-holyworths-projects.vercel.app
A4: Staging admin | B4: https://holypearls-admin-git-dev-holyworths-projects.vercel.app
A5: Staging API | B5: https://holypearls-api-staging.onrender.com
A6: Access | B6: Vercel login required for staging previews. Render free tier may cold-start (~1 min).
A7: Test personas | B7: TEST DATA people in packages/auth/src/test-people.ts (emails *@holypearls.test, passwords and MFA secrets in that file). Staff: Ada (all permissions), Tunde (STAFF_ADMIN), Folake (PAYMENT_VIEW), Kemi (CATALOGUE_MANAGE). Customers: Chidi, Amaka. ACME org: Ngozi Owner, Bola Admin, Tunde Buyer, Adaeze Location Manager (Lekki), Kemi Approver, Sam Viewer.
A8: Paystack test card | B8: 4084 0840 8408 4081, any future expiry, CVV 408, PIN 0000, OTP 123456 (Paystack's published test card; staging uses sk_test_).
A9: Email | B9: Resend can only send to the owner's address until a sending domain is verified (ATTENTION #4). Use that inbox for guest/customer email checks, or local Mailpit.
A10: Known limits | B10: Prices, delivery zones and garment decoration costs are illustrative TEST DATA. Custom large-format sizes always go to quote. Shipbubble needs its staging key.
A11: How to use | B11: Run P0 rows first. Set Result per row (Not run / Pass / Fail / Blocked / N/A), add tester, date and a bug link. Viewport '375 + 1440' means check both. The Summary sheet counts results.
A12: Order | B12: 1) Permissions & Cross-cutting P0 2) Journeys J01–J16 in order (later ones reuse earlier data) 3) Features 4) P1/P2.

Sheet Where we are
A1: Bucket | B1: Detail
A2: Done (62 of 65) | B2: Every PRD flow: platform, catalogue, configurators, checkout, Paystack, orders, projects/quotes, proofs, production, shipments + Shipbubble, accounts, workspaces, assets/templates, approvals, groups, company store, allowances, business rules, ops home, exports, refunds, staff admin, structured data, search quality, accessibility, attack suite, payment stress + NDPA, audit remediation.
A3: Blocked on owner | B3: T15-05 monitoring/runbooks is merged (#127); its Done-when needs the owner's staging switch test and restore rehearsal with timings.
A4: Not started | B4: T14-05 performance + visual regression suite; T15-07 automated cross-flow journeys 1–16 (this manual matrix covers the same journeys until then).
A5: Open PRs | B5: #138 favicon (this branch); #139, #140 dependabot bumps.
A6: Release | B6: main is ~451 commits behind dev; production last released long ago. Next release blocked on owner items: R2 buckets (ATTENTION #3), DB roles (#8, #12b), email domain (#4), Paystack live (#25).
A7: Owner-only checks | B7: T15-05 staging switch test and restore rehearsal; ATTENTION #30 hold reasons / balance timing confirmation; real prices (#13, #17, #22).

Sheet Summary
A1: Sheet | B1: Rows | C1: P0 | D1: Pass | E1: Fail | F1: Blocked | G1: Not run | H1: P0 failing
A2: Journeys | B2: 35 | C2: =COUNTIF('Journeys'!I2:I36,"P0") | D2: =COUNTIF('Journeys'!K2:K36,"Pass") | E2: =COUNTIF('Journeys'!K2:K36,"Fail") | F2: =COUNTIF('Journeys'!K2:K36,"Blocked") | G2: =COUNTIF('Journeys'!K2:K36,"Not run") | H2: =COUNTIFS('Journeys'!I2:I36,"P0",'Journeys'!K2:K36,"Fail")
A3: Features | B3: 39 | C3: =COUNTIF('Features'!I2:I40,"P0") | D3: =COUNTIF('Features'!K2:K40,"Pass") | E3: =COUNTIF('Features'!K2:K40,"Fail") | F3: =COUNTIF('Features'!K2:K40,"Blocked") | G3: =COUNTIF('Features'!K2:K40,"Not run") | H3: =COUNTIFS('Features'!I2:I40,"P0",'Features'!K2:K40,"Fail")
A4: Permissions | B4: 15 | C4: =COUNTIF('Permissions'!I2:I16,"P0") | D4: =COUNTIF('Permissions'!K2:K16,"Pass") | E4: =COUNTIF('Permissions'!K2:K16,"Fail") | F4: =COUNTIF('Permissions'!K2:K16,"Blocked") | G4: =COUNTIF('Permissions'!K2:K16,"Not run") | H4: =COUNTIFS('Permissions'!I2:I16,"P0",'Permissions'!K2:K16,"Fail")
A5: Cross-cutting | B5: 13 | C5: =COUNTIF('Cross-cutting'!I2:I14,"P0") | D5: =COUNTIF('Cross-cutting'!K2:K14,"Pass") | E5: =COUNTIF('Cross-cutting'!K2:K14,"Fail") | F5: =COUNTIF('Cross-cutting'!K2:K14,"Blocked") | G5: =COUNTIF('Cross-cutting'!K2:K14,"Not run") | H5: =COUNTIFS('Cross-cutting'!I2:I14,"P0",'Cross-cutting'!K2:K14,"Fail")
A6: Total | B6: =SUM(B2:B5) | C6: =SUM(C2:C5) | D6: =SUM(D2:D5) | E6: =SUM(E2:E5) | F6: =SUM(F2:F5) | G6: =SUM(G2:G5) | H6: =SUM(H2:H5)

Sheet Journeys
A1: ID | B1: Area | C1: Scenario | D1: Persona | E1: Preconditions | F1: Steps | G1: Expected result | H1: Refs | I1: Priority | J1: Viewport | K1: Result | L1: Tester | M1: Date | N1: Bug / notes
A2: J01.1 | B2: J01 Polo → reorder | C2: Configure custom Polo from homepage | D2: Guest | E2: Staging web open, signed out | F2: Home → Products → Staff Polo → Configure. Navy, qty 50, size matrix, left-chest embroidery, upload logo, needed-by date, Lagos address. | G2: Each step saves; price state shows ESTIMATE_READY or QUOTE_REQUIRED; choices survive refresh; no jump to empty contact form. | H2: PRD-02; T03-05 | I2: P0 | J2: 375 + 1440 | K2: Not run
A3: J01.2 | B3: J01 Polo → reorder | C3: Request final quote | D3: Guest | E3: J01.1 done | F3: Click Request Final Quote; enter name/email; submit. | G3: Confirmation shows reference; email with secure quote link arrives; configuration snapshot (colour, qty, sizes, placement, artwork version, date, destination) visible in admin Quotes. | H3: PRD-03; T03-08, T05-03 | I3: P0 | J3: 1440 | K3: Not run
A4: J01.3 | B4: J01 Polo → reorder | C4: Staff builds and sends quote | D4: Staff Ada | E4: J01.2 done | F4: Admin → Quotes → open request → build V1 lines → Send. | G4: Version V1 = SENT; customer quote page shows READY; line items match snapshot. | H4: PRD-03; T05-03 | I4: P0 | J4: 1440 | K4: Not run
A5: J01.4 | B5: J01 Polo → reorder | C5: Accept quote and pay deposit | D5: Guest | E5: J01.3 done | F5: Open secure quote link → Accept (email code) → pay deposit with Paystack test card. | G5: Accept needs recent email code; status ACCEPTED; payment DEPOSIT_PAID after webhook; order created; receipt page and email. | H5: PRD-03; T05-05, T04-05 | I5: P0 | J5: 375 + 1440 | K5: Not run
A6: J01.5 | B6: J01 Polo → reorder | C6: Proof V1 approval | D6: Staff Ada → Guest | E6: Order exists | F6: Admin → Proofs → prepare & send V1. Customer opens proof link → Approve (email code). | G6: Before approval viewer says 'Production proof preview' and AWAITING_APPROVAL; after: APPROVED; item leaves AWAITING_PREREQUISITE. | H6: PRD-04; T06-01 | I6: P0 | J6: 375 + 1440 | K6: Not run
A7: J01.6 | B7: J01 Polo → reorder | C7: Production, QC, balance, release | D7: Staff Ada | E7: Proof approved | F7: Admin → Production: move item QUEUED → IN_PRODUCTION → QUALITY_CHECK → ready. | G7: Balance becomes due at first item past QC (balance email); item READY_AWAITING_RELEASE until balance PAID, then READY_TO_DISPATCH. | H7: PRD-04; T07-01 | I7: P0 | J7: 1440 | K7: Not run
A8: J01.7 | B8: J01 Polo → reorder | C8: Ship and deliver | D8: Staff Ada | E8: Balance paid | F8: Admin → Shipments → create shipment / book courier → mark IN_TRANSIT → DELIVERED. | G8: Customer order page shows tracking and DELIVERED; shipment email(s) sent. | H8: PRD-04; T08-01, T08-06 | I8: P0 | J8: 375 | K8: Not run
A9: J01.8 | B9: J01 Polo → reorder | C9: Exact reorder and reorder with changes | D9: Guest | E9: Order DELIVERED | F9: Order page → item → Reorder. Repeat, but change artwork. | G9: Exact reorder copies spec and cites historical source; changed artwork starts 'reorder with changes'; original order unchanged. | H9: PRD-04; T08-01 | I9: P1 | J9: 1440 | K9: Not run
A10: J02.1 | B10: J02 Business Cards | C10: Direct purchase, PRICE_READY | D10: Customer Chidi | E10: Signed in | F10: Products → Business Cards → paper, sides, finish, qty, upload artwork → Add to cart → Checkout → zone delivery → pay. | G10: PRICE_READY total matches calculator; delivery rate shown; payment PAID; order CONFIRMED; receipt; no Project/Workspace step forced. | H10: PRD-02; T03-03, T04-01 | I10: P0 | J10: 375 + 1440 | K10: Not run
A11: J02.2 | B11: J02 Business Cards | C11: Proof → dispatch → reorder | D11: Staff Ada → Chidi | E11: J02.1 done | F11: Send proof → approve → production → QC → dispatch → deliver → Reorder from /account. | G11: Each status visible on /orders/[id]; reorder uses historical spec and artwork. | H11: PRD-04 | I11: P1 | J11: 1440 | K11: Not run
A12: J03.1 | B12: J03 Event project | C12: Event Project Builder | D12: Guest | E12: Signed out | F12: Home → Start a Project → Event: 250 attendees, 30 crew, Lagos, 6 weeks, upload logo/guidelines, pick items incl. custom welcome kit → Submit. | G12: Autosave each step; recommendations shown; project reference HP-P-…; submission email. | H12: PRD-03; T05-01 | I12: P0 | J12: 375 + 1440 | K12: Not run
A13: J03.2 | B13: J03 Event project | C13: Quote V1 → revision → V2 | D13: Guest + Staff | E13: J03.1 done | F13: Staff sends V1 excluding welcome kit. Customer requests revision. Staff sends V2. Customer accepts V2 and pays deposit. | G13: V1 SUPERSEDED, stays in history; customer sees 'Revised quote'; kit stays on Project outside quote and is visibly excluded. | H13: PRD-03; T05-05 | I13: P0 | J13: 1440 | K13: Not run
... A36: J16.3 | B36: J16 Failure & recovery | C36: Artwork hold, replacement proof, shipment exception | D36: Staff + Guest | E36: Order in production | F36: Put item ON_HOLD (artwork) → new proof version → approve → resume → mark shipment EXCEPTION → resolve → deliver. | G36: Hold reason visible to customer; proof versions kept; exception resolves to DELIVERED; full history on order. | H36: PRD-04; T07-01, T08-01 | I36: P1 | J36: 1440 | K36: Not run

Sheet Features
A1: ID | B1: Area | C1: Scenario | D1: Persona | E1: Preconditions | F1: Steps | G1: Expected result | H1: Refs | I1: Priority | J1: Viewport | K1: Result | L1: Tester | M1: Date | N1: Bug / notes
A2: F01 | B2: Public web | C2: Homepage, nav, footer | D2: Guest | F2: Open /, use mega-nav, footer links, wordmark. | G2: No broken links; nav works by keyboard and on mobile menu. | H2: PRD-01; T02-03 | I2: P1 | J2: 375 + 1440 | K2: Not run
A3: F02 | B3: Public web | C3: Product directory & category hubs | D3: Guest | F3: /products filters; /categories/[slug]. | G3: Correct products per category; empty states; prices show 'from'. | H3: PRD-01; T02-03 | I3: P1 | J3: 375 + 1440 | K3: Not run
A4: F03 | B4: Public web | C4: Search | D4: Guest | F4: /search with exact, typo, synonym and nonsense queries. | G4: Relevant results; typo tolerance; useful zero-result page; search logged in admin search report. | H4: PRD-01; T14-01b | I4: P1 | J4: 375 + 1440 | K4: Not run
A5: F04 | B5: Public web | C5: Content pages | D5: Guest | F5: /about, /contact, /our-work, /resources, /privacy, /privacy/processors, /photo-credits. | G5: All render; no placeholder copy; contact form submits. | H5: PRD-01; T02-06, T15-03 | I5: P2 | J5: 375 + 1440 | K5: Not run
A6: F05 | B6: SEO | C6: Indexing rules | D6: Guest | F6: View source on public pages and on /quotes, /orders, /workspace, /g, /start pages; open /sitemap.xml and /robots.txt. | G6: Public pages have canonical + JSON-LD; private pages NOINDEX and not in sitemap; no order data in metadata. | H6: PRD-01; T14-01 | I6: P1 | J6: 1440 | K6: Not run
A7: F06 | B7: SEO | C7: Content preview link | D7: Staff Ada | E7: Draft content page | F7: Admin → Content → preview → open /preview/content/[token] signed out. | G7: Preview renders; NOINDEX; token expires. | H7: T02-06 | I7: P2 | J7: 1440 | K7: Not run
A8: F07 | B8: Configurator | C8: Each product family configures | D8: Guest | F8: Configure one product per family (cards, garments, large format, signage, bags, etc.). | G8: Every option set valid; invalid combos prevented with reason; price state correct. | H8: PRD-02; T03-01..08 | I8: P0 | J8: 375 + 1440 | K8: Not run
A9: F08 | B9: Configurator | C9: Artwork upload checks | D9: Guest | F9: Upload valid PDF/PNG, low-res image, oversize file, wrong type. | G9: Preview shown; low-res warning; size/type rejected with message; file survives refresh. | H9: PRD-02; T01-05 | I9: P0 | J9: 375 + 1440 | K9: Not run
A10: F09 | B10: Configurator | C10: Saved drafts | D10: Customer Chidi | F10: Configure, leave, reopen via /configure/drafts/[id] and /account. | G10: Draft restores every choice; price updated notice if prices changed. | H10: PRD-02; T03-03, T13-01b | I10: P1 | J10: 1440 | K10: Not run
A11: F10 | B11: Configurator | C11: Custom large-format size | D11: Guest | F11: Enter a custom size. | G11: Goes to quote path (no per-m² prices yet) without losing choices. | H11: PRD-02 COM-FR-060 | I11: P2 | J11: 1440 | K11: Not run
A12: F11 | B12: Checkout | C12: Cart edits | D12: Guest | E12: 2 items in cart | F12: Change qty, remove, add again. | G12: Totals recalc; empty-cart state. | H12: PRD-02; T04-01 | I12: P0 | J12: 375 + 1440 | K12: Not run
A13: F12 | B13: Checkout | C13: Delivery zones and courier rates | D13: Guest | F13: Checkout with Lagos zone address, then outside-zone address. | G13: Zone rate inside; Shipbubble rate (or staff-set price) outside; clear message if unavailable. | H13: T04-01, T08-05 | I13: P0 | J13: 375 + 1440 | K13: Not run
A14: F13 | B14: Payments | C14: Paystack success / abandon / fail | D14: Guest | E14: Staging test key | F14: Pay with test card; then abandon; then failing card. | G14: Processing page then PAID; abandon leaves PAYMENT_DUE; fail shows retry; no duplicate orders on double-click. | H14: TECH-05; T04-03, T15-03 | I14: P0 | J14: 375 + 1440 | K14: Not run
A15: F14 | B15: Payments | C15: Payments switched off | D15: Staff Ada | F15: Admin → Payments → Settings: disable online payments; try checkout. | G15: Customer sees 'payment not available' message, no broken flow; re-enable restores. | H15: T04-05 | I15: P1 | J15: 1440 | K15: Not run
A16: F15 | B16: Payments | C16: Receipts | D16: Customer | E16: Paid order | F16: Open /orders/[id]/receipts/[receiptId]; print. | G16: Correct amounts, currency, VAT lines; printable. | H16: T04-05 | I16: P1 | J16: 1440 | K16: Not run
A17: F16 | B17: Orders | C17: Cancel and change requests | D17: Customer | E17: Order CONFIRMED | F17: /orders/[id]/cancel and /change. | G17: Allowed only in permitted states; staff see request; history kept. | H17: PRD-04; T07-03 | I17: P1 | J17: 375 + 1440 | K17: Not run
A18: F17 | B18: Orders | C18: Report a problem | D18: Customer | E18: Order DELIVERED | F18: /orders/[id]/problem with photos. | G18: Problem in Admin → Problems with order context. | H18: T08-01 | I18: P1 | J18: 375 | K18: Not run
A19: F18 | B19: Orders | C19: Guest tracking | D19: Guest | F19: /track with ref + email; wrong email. | G19: Right order opens; wrong combo gives neutral error (no enumeration). | H19: T07-03 | I19: P0 | J19: 375 | K19: Not run
A20: F19 | B20: Accounts | C20: Sign up, verify, sign in, reset | D20: New customer | F20: /sign-up → verify email → sign out → /forgot-password → reset. | G20: All emails arrive; rate limit on repeated attempts; clear errors. | H20: PRD-01; T09-01 | I20: P0 | J20: 375 + 1440 | K20: Not run
A21: F20 | B21: Accounts | C21: Profile, email change, security | D21: Customer | F21: /account/profile, change email (verify new), /account/security sessions. | G21: Email change needs verification; sign out other sessions works. | H21: T09-01b | I21: P1 | J21: 1440 | K21: Not run
A22: F21 | B22: Accounts | C22: History lists | D22: Customer | E22: Several records | F22: /account/[list] for quotes, orders, projects, drafts. | G22: Paginated; full totals; only own records. | H22: T09-01b, T00-13 | I22: P1 | J22: 375 + 1440 | K22: Not run
A23: F22 | B23: Workspace | C23: Request a workspace | D23: Customer Amaka | F23: /account/workspace → request; staff approve in Admin → Workspace requests. | G23: Pending state; approval email; workspace appears; decline path works. | H23: PRD-05; T10-01 | I23: P0 | J23: 1440 | K23: Not run
A24: F23 | B24: Workspace | C24: Team, invites, locations, roles | D24: ACME Owner | F24: Invite member, accept via /invitations, assign role + location; deactivate; try to remove last Owner. | G24: Invite email; role applied; deactivation immediate; last Owner cannot be removed. | H24: T10-01 | I24: P0 | J24: 1440 | K24: Not run
A25: F24 | B25: Workspace | C25: Overview, lists, billing, search | D25: ACME Owner | F25: Workspace home, orders, projects, billing (mixed currency), search. | G25: Attention items link to records; billing totals per currency; search scoped to org. | H25: T10-03, T00-13 | I25: P1 | J25: 375 + 1440 | K25: Not run
A26: F25 | B26: Workspace | C26: Approval rule | D26: ACME Owner | F26: /approval-rule: set threshold, separation on. | G26: Requests above threshold need approval; Buyer can't approve own request. | H26: T11-04 | I26: P0 | J26: 1440 | K26: Not run
A27: F26 | B27: Workspace | C27: Company store setup & allowances | D27: ACME Admin | F27: Stores → new → setup products, mode, allowance → publish link. | G27: Store live; allowance balances deduct and block overspend. | H27: T12-06, T12-06b | I27: P1 | J27: 1440 | K27: Not run
A28: F27 | B28: Admin | C28: Staff sign-in + MFA | D28: Staff Ada | E28: Authenticator set | F28: Admin sign-in → MFA → idle → sensitive action. | G28: MFA required; recent-MFA prompt for sensitive actions; customer site has no /admin. | H28: T00-06, T00-09 | I28: P0 | J28: 1440 | K28: Not run
A29: F28 | B29: Admin | C29: Catalogue & rules | D29: Staff Kemi (CATALOGUE) | F29: Products → edit, new; Rules → edit prices; Garment data; Merchandising; Categories hub. | G29: Changes publish to web; price updates flag drafts 'Price updated'; audit entries. | H29: T02-01, T13-01, T13-01b | I29: P1 | J29: 1440 | K29: Not run
A30: F29 | B30: Admin | C30: Operations home | D30: Staff Ada | F30: Admin home. | G30: Queues (quotes, proofs, production, problems, payments review) with correct counts and links. | H30: T13-03 | I30: P1 | J30: 1440 | K30: Not run
A31: F30 | B31: Admin | C31: Production board & holds | D31: Staff Ada | F31: Production → move cards, add/clear hold with reason. | G31: Statuses follow allowed transitions; customer sees hold reason wording. | H31: T07-01 | I31: P0 | J31: 1440 | K31: Not run
A32: F31 | B32: Admin | C32: Shipments & courier booking | D32: Staff Ada | E32: Shipbubble test key | F32: Shipments → order → book courier; webhook update. | G32: Booking durable (retry safe); tracking number on customer page. | H32: T08-06, T00-13 | I32: P1 | J32: 1440 | K32: Not run
A33: F32 | B33: Admin | C33: Refunds | D33: Staff Ada | E33: Paid order | F33: Refunds → new → partial then full. | G33: PARTIALLY_REFUNDED → REFUNDED; Paystack refund created; MFA re-check; audit. | H33: T13-05 | I33: P0 | J33: 1440 | K33: Not run
A34: F33 | B34: Admin | C34: Payments review & intents | D34: Staff Folake (VIEW) | F34: Payments, intents, reviews. | G34: Can view; every change button absent or 403. | H34: T04-05 | I34: P1 | J34: 1440 | K34: Not run
A35: F34 | B35: Admin | C35: Exports | D35: Staff Ada | F35: Exports → orders, payments, personal data. | G35: CSV downloads; personal data needs EXPORT_PERSONAL_DATA; audited. | H35: T13-03b | I35: P2 | J35: 1440 | K35: Not run
A36: F35 | B36: Admin | C36: Staff administration | D36: Staff Tunde (STAFF_ADMIN) | F36: Staff → invite, change permissions, deactivate. | G36: Changes take effect on next request; can't lock out last admin; audited. | H36: T13-05b | I36: P1 | J36: 1440 | K36: Not run
A37: F36 | B37: Admin | C37: Audit log | D37: Staff Ada | F37: Audit → filter by record/actor. | G37: Every action from this run appears with actor, record, time. | H37: T01-01 | I37: P2 | J37: 1440 | K37: Not run
A38: F37 | B38: Admin | C38: Privacy tools | D38: Staff Ada | E38: Test customer with paid order | F38: Privacy → export person → erase/anonymize. | G38: Export contains person's data; erase removes name/contact, keeps payment & tax records. | H38: T15-03 | I38: P0 | J38: 1440 | K38: Not run
A39: F38 | B39: Admin | C39: Incident switches | D39: Staff Ada | E39: Staging only | F39: Incidents → read-only mode, pause uploads, pause payments, revoke sessions, revoke guest links; then undo. | G39: Web shows matching banners/blocks; revoked sessions/links fail; MFA check; audited; all reversible. | H39: T15-05 | I39: P1 | J39: 1440 | K39: Not run
A40: F39 | B40: Admin | C40: Notifications / emails | D40: Staff Ada | F40: Trigger each customer email (quote sent, proof ready, balance due, dispatched, delivered, invite, reset). | G40: Each arrives once, correct links, branded, readable on mobile mail. | H40: PRD-00 §17 | I40: P1 | J40: 375 | K40: Not run

Sheet Permissions
A1: ID | B1: Area | C1: Scenario | D1: Persona | E1: Preconditions | F1: Steps | G1: Expected result | H1: Refs | I1: Priority | J1: Viewport | K1: Result | L1: Tester | M1: Date | N1: Bug / notes
A2: P01 | B2: Customer isolation | C2: Customer A opens Customer B's records | D2: Customer Chidi | E2: Amaka has config, project, quote, proof, order, receipt | F2: Signed in as Chidi, paste each of Amaka's URLs. | G2: 404/403 for every record; no data leak in page or network. | H2: TECH-03 §17 | I2: P0 | J2: 1440 | K2: Not run
A3: P02 | B3: Guest links | C3: Guest link for one order opens another | D3: Guest | E3: Two guest orders | F3: Edit the id in a guest order/proof/quote link. | G3: Denied; no list of that customer's other orders. | H3: TECH-03 §17 | I3: P0 | J3: 1440 | K3: Not run
A4: P03 | B4: Guest links | C4: Expired / revoked links | D4: Guest | E4: Link revoked in admin or expired | F4: Open the link. | G4: Clear 'link no longer valid' with resend option; no data. | H4: TECH-03 §17 | I4: P0 | J4: 375 | K4: Not run
A5: P04 | B5: Organizations | C5: Org A reads Org B | D5: ACME member | E5: Second org exists | F5: Paste Org B workspace URLs. | G5: Denied. | H5: TECH-03 §17 | I5: P0 | J5: 1440 | K5: Not run
A6: P05 | B6: Locations | C6: Lekki manager sees VI | D6: Location Mgr Adaeze | E6: VI orders exist | F6: Browse orders/groups/search; paste VI record URL. | G6: VI records absent and denied. | H6: TECH-03 §17 | I6: P0 | J6: 1440 | K6: Not run
A7: P06 | B7: Participants | C7: Participant reads another submission | D7: Participant | E7: Two participant links | F7: Swap participant id in /collections/submissions/[id]. | G7: Denied; no peer names. | H7: TECH-03 §17 | I7: P0 | J7: 375 | K7: Not run
A8: P07 | B8: Roles | C8: Viewer cannot change anything | D8: Viewer Sam | F8: Try every edit/approve/accept/invite button and direct API calls. | G8: Buttons hidden/disabled; API 403. | H8: TECH-03 §17 | I8: P0 | J8: 1440 | K8: Not run
A9: P08 | B9: Roles | C9: Approver cannot accept quote | D9: Approver Kemi | E9: Quote READY | F9: Open quote → Accept. | G9: Blocked unless separately granted accept-quote. | H9: TECH-03 §17 | I9: P0 | J9: 1440 | K9: Not run
A10: P09 | B10: Roles | C10: Buyer approves own request | D10: Buyer Tunde | E10: Separation on | F10: Submit request, try to approve it. | G10: Blocked. | H10: TECH-03 §17 | I10: P0 | J10: 1440 | K10: Not run
A11: P10 | B11: Roles | C11: Remove last Owner | D11: ACME Owner | E11: Single owner | F11: Team → remove/demote self. | G11: Blocked with reason. | H11: TECH-03 §17 | I11: P0 | J11: 1440 | K11: Not run
A12: P11 | B12: Roles | C12: Deactivated member | D12: ACME Admin Bola | E12: Bola signed in in another browser | F12: Owner deactivates Bola; Bola refreshes. | G12: Access lost immediately; past audit actions remain. | H12: TECH-03 §17 | I12: P0 | J12: 1440 | K12: Not run
A13: P12 | B13: Staff | C13: Staff without permission | D13: Staff Kemi (CATALOGUE only) | F13: Open payments, refunds, staff, privacy pages / actions. | G13: 403 / hidden on each. | H13: TECH-03 §17 | I13: P0 | J13: 1440 | K13: Not run
A14: P13 | B14: Step-up | C14: Accept quote / approve proof without recent email code | D14: Guest | E14: Old session | F14: Accept quote and approve proof without fresh code. | G14: Asks for email code; fails without it. | H14: TECH-03 §17 | I14: P0 | J14: 375 | K14: Not run
A15: P14 | B15: Abuse | C15: Rate limits | D15: Guest | F15: Hammer sign-in, reset, /track, help form. | G15: 429 with friendly message after limit. | H15: T15-01 | I15: P1 | J15: 1440 | K15: Not run
A16: P15 | B16: Headers | C16: Security headers | D16: Guest | F16: DevTools → response headers on web, admin, API. | G16: CSP, HSTS, X-Frame-Options/frame-ancestors, Referrer-Policy present. | H16: T15-01 | I16: P1 | J16: 1440 | K16: Not run

Sheet Cross-cutting
A1: ID | B1: Area | C1: Scenario | D1: Persona | E1: Preconditions | F1: Steps | G1: Expected result | H1: Refs | I1: Priority | J1: Viewport | K1: Result | L1: Tester | M1: Date | N1: Bug / notes
A2: X01 | B2: Responsive | C2: Key screens at 375 px | D2: Any | F2: Home, PDP/configurator, cart, checkout, project builder, quote, proof, order, participant form, store, workspace home. | G2: No horizontal scroll; tap targets ≥44 px; sticky actions don't hide content. | H2: DESIGN-SYSTEM | I2: P0 | J2: 375 | K2: Not run
A3: X02 | B3: Responsive | C3: Same screens at 1440 px vs Pen | D3: Any | E3: Pen open | F3: Compare with SCREEN-MAP frames. | G3: Matches layout, spacing, type; log differences. | H3: SCREEN-MAP | I3: P1 | J3: 1440 | K3: Not run
A4: X03 | B4: Responsive | C4: 320 px + 200% text zoom | D4: Any | F4: Product, search, case study, checkout. | G4: Reflows without loss. | H4: T14-03 | I4: P2 | J4: 320 | K4: Not run
A5: X04 | B5: Accessibility | C5: Keyboard only | D5: Any | F5: Complete J02 with keyboard only. | G5: Visible focus; logical order; dialogs trap and return focus; skip link. | H5: T14-03 | I5: P0 | J5: 1440 | K5: Not run
A6: X05 | B6: Accessibility | C6: Screen reader spot check | D6: Any | E6: VoiceOver | F6: Configurator, checkout, proof decision. | G6: Labels, errors and status changes announced. | H6: T14-03 | I6: P1 | J6: 375 + 1440 | K6: Not run
A7: X06 | B7: Accessibility | C7: Reduced motion & contrast | D7: Any | E7: OS reduced motion on | F7: Browse key screens. | G7: Animations reduced; text contrast AA. | H7: T14-03 | I7: P2 | J7: 1440 | K7: Not run
A8: X07 | B8: Browsers | C8: Cross-browser | D8: Any | F8: Run J02 on Safari iOS, Chrome Android, Safari macOS, Chrome, Firefox, Edge. | G8: Works on each; Paystack popup opens on mobile. | H8: TECH-07 | I8: P1 | J8: 375 + 1440 | K8: Not run
A9: X08 | B9: Forms | C9: New form controls | D9: Any | F9: Date picker, styled selects, choice controls with mouse, touch and keyboard. | G9: Usable on touch; sizes moderate on desktop; native fallback OK. | H9: PR #136 | I9: P1 | J9: 375 + 1440 | K9: Not run
A10: X09 | B10: Errors | C10: Error / loading / not-found states | D10: Any | F10: Open bad URL; throttle network; stop API (local). | G10: Branded 404, loading skeletons, friendly error with retry. | H10: T00-05 | I10: P2 | J10: 375 + 1440 | K10: Not run
A11: X10 | B11: Money | C11: Currency, VAT, rounding | D11: Customer | F11: Check totals across PDP, cart, checkout, quote, receipt, refund. | G11: Same amount everywhere; kobo rounding consistent; USD only where enabled. | H11: TECH-05 | I11: P0 | J11: 1440 | K11: Not run
A12: X11 | B12: Concurrency | C12: Double-click & two tabs | D12: Guest | F12: Double-click Pay / Accept / Approve / Submit; act in two tabs at once. | G12: One record and one payment; second tab gets version conflict message. | H12: T15-03 | I12: P0 | J12: 1440 | K12: Not run
A13: X12 | B13: Branding | C13: Favicon & meta | D13: Any | F13: Check tab icon light/dark, apple-touch-icon, OG image share preview. | G13: Circular favicon on white; OG previews correct. | H13: PR #138 | I13: P2 | J13: 1440 | K13: Not run
A14: X13 | B14: Performance | C14: Slow 3G feel | D14: Guest | E14: DevTools throttling | F14: Load home, PDP, configurator. | G14: Usable within a few seconds; images lazy load; no layout jump. | H14: T14-05 (TODO) | I14: P2 | J14: 375 | K14: Not run
